bsv_middleware/__init__.py
bsv_middleware/exceptions.py
bsv_middleware/interfaces.py
bsv_middleware/py_sdk_bridge.py
bsv_middleware/types.py
bsv_middleware/wallet_adapter.py
bsv_middleware/django/__init__.py
bsv_middleware/django/auth_middleware.py
bsv_middleware/django/session_manager.py
bsv_middleware/django/transport.py
bsv_middleware-2.0.2.dist-info/METADATA
bsv_middleware-2.0.2.dist-info/WHEEL
bsv_middleware-2.0.2.dist-info/top_level.txt
bsv_middleware-2.0.2.dist-info/RECORD
