Metadata-Version: 2.4
Name: bsv-middleware
Version: 2.0.2
Summary: Django middleware for BSV blockchain authentication and payment processing
Author-email: BSV Middleware Team <team@bsv-middleware.com>
Maintainer-email: BSV Middleware Team <team@bsv-middleware.com>
License: MIT
Project-URL: Homepage, https://github.com/bsv-blockchain/py-middleware
Project-URL: Documentation, https://py-middleware.readthedocs.io/
Project-URL: Repository, https://github.com/bsv-blockchain/py-middleware.git
Project-URL: Issues, https://github.com/bsv-blockchain/py-middleware/issues
Project-URL: Changelog, https://github.com/bsv-blockchain/py-middleware/blob/main/CHANGELOG.md
Keywords: bsv,bitcoin,blockchain,django,middleware,authentication,payment,cryptocurrency
Classifier: Development Status :: 4 - Beta
Classifier: Intended Audience :: Developers
Classifier: License :: OSI Approved :: MIT License
Classifier: Operating System :: OS Independent
Classifier: Programming Language :: Python :: 3
Classifier: Programming Language :: Python :: 3.8
Classifier: Programming Language :: Python :: 3.9
Classifier: Programming Language :: Python :: 3.10
Classifier: Programming Language :: Python :: 3.11
Classifier: Framework :: Django
Classifier: Framework :: Django :: 3.2
Classifier: Framework :: Django :: 4.0
Classifier: Framework :: Django :: 4.1
Classifier: Framework :: Django :: 4.2
Classifier: Topic :: Internet :: WWW/HTTP :: HTTP Servers
Classifier: Topic :: Internet :: WWW/HTTP :: WSGI :: Middleware
Classifier: Topic :: Security :: Cryptography
Classifier: Topic :: Software Development :: Libraries :: Python Modules
Requires-Python: >=3.8
Requires-Dist: bsv-sdk>=2.0.0b1
Requires-Dist: django<5.0.0,>=3.2.0
Requires-Dist: pydantic<3.0.0,>=1.8.0
Requires-Dist: typing-extensions>=4.0.0
Provides-Extra: dev
Requires-Dist: pytest>=7.0.0; extra == "dev"
Requires-Dist: pytest-django>=4.5.0; extra == "dev"
Requires-Dist: pytest-cov>=4.0.0; extra == "dev"
Requires-Dist: pytest-mock>=3.6.0; extra == "dev"
Requires-Dist: pytest-asyncio>=0.18.0; extra == "dev"
Requires-Dist: black>=22.0.0; extra == "dev"
Requires-Dist: ruff>=0.1.0; extra == "dev"
Requires-Dist: mypy>=0.910; extra == "dev"
Requires-Dist: flake8>=4.0.0; extra == "dev"
Requires-Dist: isort>=5.10.0; extra == "dev"
Requires-Dist: pre-commit>=2.15.0; extra == "dev"
Provides-Extra: docs
Requires-Dist: sphinx>=4.0.0; extra == "docs"
Requires-Dist: sphinx-rtd-theme>=1.0.0; extra == "docs"
Requires-Dist: myst-parser>=0.18.0; extra == "docs"
